{
	"credit": "Made with Blockbench",
	"texture_size": [32, 32],
	"textures": {
		"0": "./vita",
		"particle": "./vita"
	},
	"elements": [
		{
			"name": "saw2",
			"from": [8, 7, -6],
			"to": [8, 8, 2],
			"rotation": {"angle": 0, "axis": "y", "origin": [9, 8.5, 11]},
			"faces": {
				"north": {"uv": [0.5, 0, 1, 1], "texture": "#0", "tintindex": 0},
				"east": {"uv": [4, 6, 0, 6.5], "texture": "#0", "tintindex": 0},
				"south": {"uv": [3.5, 0, 4, 1], "texture": "#0", "tintindex": 0},
				"west": {"uv": [0, 6, 4, 6.5], "texture": "#0", "tintindex": 0},
				"up": {"uv": [0.5, 0, 4, 0.5], "rotation": 90, "texture": "#0", "tintindex": 0},
				"down": {"uv": [4, 0.5, 0.5, 1], "rotation": 90, "texture": "#0", "tintindex": 0}
			}
		},
		{
			"from": [7, 6.5, 2],
			"to": [9, 8.5, 10],
			"rotation": {"angle": 0, "axis": "y", "origin": [8.5, 9, 10.5]},
			"faces": {
				"north": {"uv": [1, 5, 2, 6], "texture": "#0", "tintindex": 0},
				"east": {"uv": [8, 6, 4, 7], "texture": "#0", "tintindex": 0},
				"south": {"uv": [0, 5, 1, 6], "texture": "#0", "tintindex": 0},
				"west": {"uv": [4, 6, 8, 7], "texture": "#0", "tintindex": 0},
				"up": {"uv": [4, 4.5, 8, 5.5], "rotation": 90, "texture": "#0", "tintindex": 0},
				"down": {"uv": [4, 6, 8, 7], "rotation": 270, "texture": "#0", "tintindex": 0}
			}
		},
		{
			"from": [7, 9, 9.5],
			"to": [9, 13, 11.5],
			"rotation": {"angle": 22.5, "axis": "x", "origin": [8.5, 9, 11]},
			"faces": {
				"north": {"uv": [3, 4, 4, 6], "texture": "#0", "tintindex": 0},
				"east": {"uv": [2, 3, 1, 5], "texture": "#0", "tintindex": 0},
				"south": {"uv": [1, 3, 0, 5], "texture": "#0", "tintindex": 0},
				"west": {"uv": [2, 4, 3, 6], "texture": "#0", "tintindex": 0},
				"up": {"uv": [2, 3, 3, 4], "texture": "#0", "tintindex": 0},
				"down": {"uv": [2, 3, 3, 4], "rotation": 270, "texture": "#0", "tintindex": 0}
			}
		},
		{
			"from": [8, 1.5, 2],
			"to": [8, 9.5, 18],
			"rotation": {"angle": 0, "axis": "y", "origin": [15, 9, 19.5]},
			"faces": {
				"north": {"uv": [10, 9, 10.33333, 9.33333], "texture": "#0"},
				"east": {"uv": [12, 5.5, 4, 9.5], "texture": "#0"},
				"south": {"uv": [10, 9.33333, 10.33333, 9.66667], "texture": "#0"},
				"west": {"uv": [4, 5.5, 12, 9.5], "texture": "#0"},
				"up": {"uv": [10, 9.33333, 10.33333, 9.66667], "texture": "#0"},
				"down": {"uv": [10, 9, 10.33333, 9.33333], "texture": "#0"}
			}
		}
	],
	"display": {
		"thirdperson_righthand": {
			"rotation": [33, 0.5, 1],
			"translation": [0, 3.25, -0.75]
		},
		"thirdperson_lefthand": {
			"rotation": [33, 0.5, 1],
			"translation": [0, 3.25, -0.75]
		},
		"firstperson_righthand": {
			"rotation": [60, 3, -3],
			"translation": [4.5, 0.75, -4]
		},
		"firstperson_lefthand": {
			"rotation": [60, 3, -3],
			"translation": [4.5, 0.75, -4]
		},
		"ground": {
			"rotation": [0, 0, 90],
			"translation": [-2, -2, 0.75]
		},
		"gui": {
			"rotation": [90, 60, -90],
			"translation": [2.25, 1.5, 0],
			"scale": [0.77, 0.77, 0.77]
		},
		"head": {
			"rotation": [-19, -180, 0],
			"translation": [0.5, 9, -10.5]
		},
		"fixed": {
			"rotation": [90, -60, 90],
			"translation": [-4.75, 4.25, 0],
			"scale": [2, 2, 2]
		}
	}
}